soft404/__init__.py
soft404/clf.joblib
soft404/convert_to_text.py
soft404/predict.py
soft404/train.py
soft404/utils.py
soft_404-0.4.0.dist-info/METADATA
soft_404-0.4.0.dist-info/WHEEL
soft_404-0.4.0.dist-info/top_level.txt
soft_404-0.4.0.dist-info/RECORD
