Metadata-Version: 2.1
Name: soft-404
Version: 0.4.0
Summary: A classifier for detecting soft 404 pages
Home-page: https://github.com/TeamHG-Memex/soft404
Author: Konstantin Lopuhin
Author-email: kostia.lopuhin@gmail.com
License: MIT
Platform: UNKNOWN
Classifier: Development Status :: 3 - Alpha
Classifier: Topic :: Internet :: WWW/HTTP :: Indexing/Search
Classifier: License :: OSI Approved :: MIT License
Classifier: Programming Language :: Python
Classifier: Programming Language :: Python :: 3
Classifier: Programming Language :: Python :: 3.6
Classifier: Programming Language :: Python :: 3.7
Classifier: Programming Language :: Python :: 3.8
Requires-Dist: langdetect (==1.0.8)
Requires-Dist: lxml (==4.5.2)
Requires-Dist: numpy (==1.19.1)
Requires-Dist: parsel (>=1.6.0)
Requires-Dist: scikit-learn (==0.23.2)
Requires-Dist: joblib (==0.16.0)
Requires-Dist: scipy (>=1.5.2)
Requires-Dist: webstruct (==0.6)
Requires-Dist: html-text (==0.5.2)
